CONTRIBUTING.md
LICENSE
MANIFEST.in
README.md
codecov.yml
setup.cfg
setup.py
tox.ini
docs/aiohttp.md
docs/flask.md
docs/sanic.md
docs/webob.md
docs/_static/graphql-server-logo.svg
graphql_server/__init__.py
graphql_server/error.py
graphql_server/render_graphiql.py
graphql_server/utils.py
graphql_server/version.py
graphql_server/aiohttp/__init__.py
graphql_server/aiohttp/graphqlview.py
graphql_server/flask/__init__.py
graphql_server/flask/graphqlview.py
graphql_server/quart/__init__.py
graphql_server/quart/graphqlview.py
graphql_server/sanic/__init__.py
graphql_server/sanic/graphqlview.py
graphql_server/webob/__init__.py
graphql_server/webob/graphqlview.py
graphql_server_custom.egg-info/PKG-INFO
graphql_server_custom.egg-info/SOURCES.txt
graphql_server_custom.egg-info/dependency_links.txt
graphql_server_custom.egg-info/not-zip-safe
graphql_server_custom.egg-info/requires.txt
graphql_server_custom.egg-info/top_level.txt
tests/__init__.py
tests/schema.py
tests/test_asyncio.py
tests/test_error.py
tests/test_helpers.py
tests/test_query.py
tests/test_version.py
tests/utils.py
tests/aiohttp/__init__.py
tests/aiohttp/app.py
tests/aiohttp/conftest.py
tests/aiohttp/schema.py
tests/aiohttp/test_graphiqlview.py
tests/aiohttp/test_graphqlview.py
tests/flask/__init__.py
tests/flask/app.py
tests/flask/conftest.py
tests/flask/schema.py
tests/flask/test_graphiqlview.py
tests/flask/test_graphqlview.py
tests/quart/__init__.py
tests/quart/app.py
tests/quart/conftest.py
tests/quart/schema.py
tests/quart/test_graphiqlview.py
tests/quart/test_graphqlview.py
tests/sanic/__init__.py
tests/sanic/app.py
tests/sanic/conftest.py
tests/sanic/schema.py
tests/sanic/test_graphiqlview.py
tests/sanic/test_graphqlview.py
tests/webob/__init__.py
tests/webob/app.py
tests/webob/conftest.py
tests/webob/schema.py
tests/webob/test_graphiqlview.py
tests/webob/test_graphqlview.py