Metadata-Version: 2.1
Name: graphql-server-custom
Version: 3.0.0b5
Summary: GraphQL Server tools for powering your server
Home-page: https://github.com/graphql-python/graphql-server
Author: Syrus Akbary
Author-email: me@syrusakbary.com
License: MIT
Download-URL: https://github.com/graphql-python/graphql-server/releases
Keywords: api graphql protocol rest
Platform: any
Classifier: Development Status :: 3 - Alpha
Classifier: Intended Audience :: Developers
Classifier: Topic :: Software Development :: Libraries
Classifier: Programming Language :: Python :: 3.6
Classifier: Programming Language :: Python :: 3.7
Classifier: Programming Language :: Python :: 3.8
Classifier: Programming Language :: Python :: 3.9
Classifier: Programming Language :: Python :: 3.10
Classifier: License :: OSI Approved :: MIT License
Provides-Extra: all
Provides-Extra: test
Provides-Extra: dev
Provides-Extra: flask
Provides-Extra: sanic
Provides-Extra: webob
Provides-Extra: aiohttp
Provides-Extra: quart
